pynih/__init__.py
pynih/apis.py
pynih-0.1.3.dist-info/LICENSE
pynih-0.1.3.dist-info/METADATA
pynih-0.1.3.dist-info/WHEEL
pynih-0.1.3.dist-info/RECORD
