Metadata-Version: 2.1
Name: pynih
Version: 0.1.3
Summary: python wrapper for nih reporter apis --> https://api.reporter.nih.gov/
Home-page: https://github.com/jermwatt/pynih
License: MIT
Author: Jeremy Watt
Author-email: jermwatt@gmail.com
Requires-Python: >=3.9.1,<3.11
Classifier: License :: OSI Approved :: MIT License
Classifier: Programming Language :: Python :: 3
Classifier: Programming Language :: Python :: 3.10
Requires-Dist: requests (>=2.28.2,<3.0.0)
